magicformulabr/__init__.py
magicformulabr/main.py
magicformulabr-0.2.1.dist-info/licenses/LICENSE
magicformulabr-0.2.1.dist-info/METADATA
magicformulabr-0.2.1.dist-info/WHEEL
magicformulabr-0.2.1.dist-info/entry_points.txt
magicformulabr-0.2.1.dist-info/top_level.txt
magicformulabr-0.2.1.dist-info/RECORD
