Metadata-Version: 2.4
Name: magicformulabr
Version: 0.2.1
Summary: Magic Formula script for companies listed at Bovespa.
Author: Thobias Salazar Trevisan
License: MIT License
Project-URL: Homepage, https://github.com/thobiast/magicformulabr
Project-URL: Source, https://github.com/thobiast/magicformulabr
Requires-Python: >=3.7
License-File: LICENSE
Requires-Dist: requests
Requires-Dist: pandas
Requires-Dist: lxml
Dynamic: license-file
